Metadata-Version: 2.4
Name: web2json-agent
Version: 1.1.3
Summary: Web Structured Data Extraction Agent
Author-email: YangGuoqiang <1041206149@qq.com>
License-Expression: Apache-2.0
Project-URL: Homepage, https://github.com/ccprocessor/web2json-agent
Project-URL: Repository, https://github.com/ccprocessor/web2json-agent.git
Project-URL: Bug Tracker, https://github.com/ccprocessor/web2json-agent/issues
Keywords: web scraping,html parser,ai agent,code generation,langchain,web automation
Classifier: Development Status :: 4 - Beta
Classifier: Intended Audience :: Developers
Classifier: Programming Language :: Python :: 3
Classifier: Programming Language :: Python :: 3.10
Classifier: Programming Language :: Python :: 3.11
Classifier: Programming Language :: Python :: 3.12
Classifier: Programming Language :: Python :: 3.13
Classifier: Topic :: Software Development :: Code Generators
Classifier: Topic :: Internet :: WWW/HTTP :: Indexing/Search
Classifier: Topic :: Text Processing :: Markup :: HTML
Requires-Python: >=3.10
License-File: LICENSE
Requires-Dist: langchain==1.0.1
Requires-Dist: langchain-core==1.0.5
Requires-Dist: langchain-openai==1.0.3
Requires-Dist: langchain-anthropic==1.1.0
Requires-Dist: openai==2.8.1
Requires-Dist: pydantic==2.10.3
Requires-Dist: pydantic-settings==2.6.1
Requires-Dist: python-dotenv==1.1.0
Requires-Dist: loguru==0.7.3
Requires-Dist: DrissionPage==4.1.1.2
Requires-Dist: beautifulsoup4==4.12.3
Requires-Dist: lxml==5.3.0
Requires-Dist: requests==2.32.3
Requires-Dist: numpy>=1.24.0
Requires-Dist: scikit-learn>=1.3.0
Requires-Dist: fastapi==0.109.0
Requires-Dist: uvicorn[standard]==0.27.0
Requires-Dist: python-multipart==0.0.6
Requires-Dist: aiofiles==23.2.1
Provides-Extra: dev
Requires-Dist: pytest>=7.0.0; extra == "dev"
Requires-Dist: pytest-cov>=4.0.0; extra == "dev"
Requires-Dist: black>=23.0.0; extra == "dev"
Requires-Dist: flake8>=6.0.0; extra == "dev"
Requires-Dist: mypy>=1.0.0; extra == "dev"
Dynamic: license-file
